{
    "/js/app.js": "/js/app.js",
    "/css/app.css": "/css/app.css",
    "/js/app.5b34d30c709d43353b2d.hot-update.js": "/js/app.5b34d30c709d43353b2d.hot-update.js",
    "/js/app.462e37091e2fa7d0ee19.hot-update.js": "/js/app.462e37091e2fa7d0ee19.hot-update.js",
    "/js/app.6815c202bb142c138b3c.hot-update.js": "/js/app.6815c202bb142c138b3c.hot-update.js",
    "/js/app.6aac2a7ff7489e7fdbf6.hot-update.js": "/js/app.6aac2a7ff7489e7fdbf6.hot-update.js",
    "/js/app.d0095a4edf0d0d6bc427.hot-update.js": "/js/app.d0095a4edf0d0d6bc427.hot-update.js",
    "/js/app.cac8cf300b6f3e32abd8.hot-update.js": "/js/app.cac8cf300b6f3e32abd8.hot-update.js",
    "/js/app.c706699f3732e3a0ac43.hot-update.js": "/js/app.c706699f3732e3a0ac43.hot-update.js",
    "/js/app.d6db06176b80cb3cd302.hot-update.js": "/js/app.d6db06176b80cb3cd302.hot-update.js",
    "/js/app.e8cfc5d364e186f49880.hot-update.js": "/js/app.e8cfc5d364e186f49880.hot-update.js",
    "/js/app.8523113db166cb5ce023.hot-update.js": "/js/app.8523113db166cb5ce023.hot-update.js",
    "/js/app.e25a069a43f5937707a6.hot-update.js": "/js/app.e25a069a43f5937707a6.hot-update.js",
    "/js/app.3981d66a55c583e7a01c.hot-update.js": "/js/app.3981d66a55c583e7a01c.hot-update.js",
    "/js/app.22f80cfbc801a37ba0c5.hot-update.js": "/js/app.22f80cfbc801a37ba0c5.hot-update.js",
    "/js/app.d25761220a5a24ff1544.hot-update.js": "/js/app.d25761220a5a24ff1544.hot-update.js",
    "/js/app.3ede886c31e9cf866229.hot-update.js": "/js/app.3ede886c31e9cf866229.hot-update.js",
    "/js/app.f6cd07fa50666309ffe2.hot-update.js": "/js/app.f6cd07fa50666309ffe2.hot-update.js",
    "/js/app.bd02c4bba244e1f50deb.hot-update.js": "/js/app.bd02c4bba244e1f50deb.hot-update.js",
    "/js/app.3d9f3fcfa7f5b657845a.hot-update.js": "/js/app.3d9f3fcfa7f5b657845a.hot-update.js",
    "/js/app.212a3ed38b413fa3b31c.hot-update.js": "/js/app.212a3ed38b413fa3b31c.hot-update.js",
    "/js/app.fa4a4afb59b8ef0d1036.hot-update.js": "/js/app.fa4a4afb59b8ef0d1036.hot-update.js",
    "/js/app.2b46680b606ae60c6484.hot-update.js": "/js/app.2b46680b606ae60c6484.hot-update.js",
    "/js/app.7db38aa613531af119a4.hot-update.js": "/js/app.7db38aa613531af119a4.hot-update.js"
}
